{
  "type": "minecraft:crafting_shapeless",
  "ingredients": [
    {
      "item": "pixelsofmc:bio_compound"
    },
    {
      "item": "pixelsofmc:bio_compound"
    },
    {
      "item": "minecraft:chorus_flower"
    },
    {
      "item": "minecraft:chorus_fruit"
    },
    {
      "item": "minecraft:chorus_fruit"
    },
    {
      "item": "minecraft:dragon_breath"
    },
    {
      "item": "minecraft:popped_chorus_fruit"
    },
    {
      "tag": "forge:ender_pearls"
    },
    {
      "tag": "forge:ender_pearls"
    }
  ],
  "result": {
    "item": "pixelsofmc:repelling_compound",
    "count": 2
  }
}