{
  "type": "pixelsofmc:pixel_splitting",
  "colors": [
    {
      "B": 165,
      "G": 228,
      "R": 129
    },
    {
      "B": 106,
      "G": 178,
      "R": 66
    },
    {
      "B": 66,
      "G": 95,
      "R": 37
    }
  ],
  "input": {
    "count": 1,
    "ingredient": {
      "item": "pixelsofmc:chromium_ingot"
    }
  },
  "outputs": [
    {
      "count": 10,
      "ingredient": {
        "item": "pixelsofmc:pixel_pile"
      }
    },
    {
      "count": 1,
      "ingredient": {
        "item": "pixelsofmc:pixel"
      }
    }
  ],
  "structure": "element.pixelsofmc.chromium"
}