{
  "type": "pixelsofmc:pixel_splitting",
  "colors": [
    {
      "B": 207,
      "G": 140,
      "R": 192
    },
    {
      "B": 158,
      "G": 63,
      "R": 114
    },
    {
      "B": 77,
      "G": 31,
      "R": 57
    }
  ],
  "input": {
    "count": 1,
    "ingredient": {
      "item": "pixelsofmc:potassium_ingot"
    }
  },
  "outputs": [
    {
      "count": 10,
      "ingredient": {
        "item": "pixelsofmc:pixel_pile"
      }
    },
    {
      "count": 1,
      "ingredient": {
        "item": "pixelsofmc:pixel"
      }
    }
  ],
  "structure": "element.pixelsofmc.potassium"
}